postale/__init__.py
postale-1.3.4.dist-info/METADATA
postale-1.3.4.dist-info/WHEEL
postale-1.3.4.dist-info/licenses/LICENSE
postale-1.3.4.dist-info/RECORD
